{
  "files": [
    {
      "features": [
        {
          "FEATURES_METHOD_INVOCATION": {},
          "FEATURES_TYPEACCESS": {},
          "FEATURES_VARS": {},
          "S10_METHOD_CALL_WITH_NULL_GUARD": "false",
          "S11_FAULTY_CLASS_EXCEPTION_TYPE": "false",
          "S12_METHOD_CALL_WITH_TRY_CATCH": "false",
          "S13_TYPE_OF_FAULTY_STATEMENT_AFTER_1": "",
          "S13_TYPE_OF_FAULTY_STATEMENT_AFTER_2": "",
          "S13_TYPE_OF_FAULTY_STATEMENT_AFTER_3": "",
          "S13_TYPE_OF_FAULTY_STATEMENT_BEFORE_1": "",
          "S13_TYPE_OF_FAULTY_STATEMENT_BEFORE_2": "",
          "S13_TYPE_OF_FAULTY_STATEMENT_BEFORE_3": "",
          "S14_TYPE_OF_FAULTY_STATEMENT_PARENT": "Method",
          "S15_HAS_OBJECTIVE_METHOD_CALL": "true",
          "S16_HAS_Invocations_Prone_Exception": "false",
          "S18_In_Synchronized_Method": "false",
          "S1_LOCAL_VAR_NOT_ASSIGNED": "false",
          "S1_LOCAL_VAR_NOT_USED": "false",
          "S2_SIMILAR_OBJECT_TYPE_WITH_NORMAL_GUARD": "false",
          "S2_SIMILAR_OBJECT_TYPE_WITH_NULL_GUARD": "false",
          "S3_TYPE_OF_FAULTY_STATEMENT": "Switch",
          "S4_Field_NOT_ASSIGNED": "false",
          "S4_Field_NOT_USED": "false",
          "S5_SIMILAR_PRIMITIVE_TYPE_WITH_NORMAL_GUARD": "false",
          "S5_SIMILAR_PRIMITIVE_TYPE_WITH_NULL_GUARD": "false",
          "S6_METHOD_THROWS_EXCEPTION": "false",
          "S7_OBJECT_USED_IN_ASSIGNMENT": "false",
          "S8_PRIMITIVE_USED_IN_ASSIGNMENT": "false",
          "S9_METHOD_CALL_WITH_NORMAL_GUARD": "false",
          "ast_info": {
            "dst": "null",
            "dst_parent": "null",
            "dst_parent_type": "null",
            "dst_type": "null",
            "operator": "DEL",
            "src": "case com.google.javascript.rhino.Token.DELPROP :\n    return true;",
            "src_parent": "switch (n.getType()) {\n    case com.google.javascript.rhino.Token.TRUE :\n    case com.google.javascript.rhino.Token.FALSE :\n    case com.google.javascript.rhino.Token.EQ :\n    case com.google.javascript.rhino.Token.NE :\n    case com.google.javascript.rhino.Token.SHEQ :\n    case com.google.javascript.rhino.Token.SHNE :\n    case com.google.javascript.rhino.Token.LT :\n    case com.google.javascript.rhino.Token.GT :\n    case com.google.javascript.rhino.Token.LE :\n    case com.google.javascript.rhino.Token.GE :\n    case com.google.javascript.rhino.Token.IN :\n    case com.google.javascript.rhino.Token.INSTANCEOF :\n    case com.google.javascript.rhino.Token.NOT :\n    case com.google.javascript.rhino.Token.DELPROP :\n        return true;\n    default :\n        return false;\n}",
            "src_parent_type": "Switch",
            "src_type": "Case"
          }
        },
        {
          "FEATURES_METHOD_INVOCATION": {},
          "FEATURES_TYPEACCESS": {},
          "FEATURES_VARS": {},
          "S10_METHOD_CALL_WITH_NULL_GUARD": "false",
          "S11_FAULTY_CLASS_EXCEPTION_TYPE": "false",
          "S12_METHOD_CALL_WITH_TRY_CATCH": "false",
          "S13_TYPE_OF_FAULTY_STATEMENT_AFTER_1": "",
          "S13_TYPE_OF_FAULTY_STATEMENT_AFTER_2": "",
          "S13_TYPE_OF_FAULTY_STATEMENT_AFTER_3": "",
          "S13_TYPE_OF_FAULTY_STATEMENT_BEFORE_1": "",
          "S13_TYPE_OF_FAULTY_STATEMENT_BEFORE_2": "",
          "S13_TYPE_OF_FAULTY_STATEMENT_BEFORE_3": "",
          "S14_TYPE_OF_FAULTY_STATEMENT_PARENT": "Method",
          "S15_HAS_OBJECTIVE_METHOD_CALL": "true",
          "S16_HAS_Invocations_Prone_Exception": "false",
          "S18_In_Synchronized_Method": "false",
          "S1_LOCAL_VAR_NOT_ASSIGNED": "false",
          "S1_LOCAL_VAR_NOT_USED": "false",
          "S2_SIMILAR_OBJECT_TYPE_WITH_NORMAL_GUARD": "false",
          "S2_SIMILAR_OBJECT_TYPE_WITH_NULL_GUARD": "false",
          "S3_TYPE_OF_FAULTY_STATEMENT": "Switch",
          "S4_Field_NOT_ASSIGNED": "false",
          "S4_Field_NOT_USED": "false",
          "S5_SIMILAR_PRIMITIVE_TYPE_WITH_NORMAL_GUARD": "false",
          "S5_SIMILAR_PRIMITIVE_TYPE_WITH_NULL_GUARD": "false",
          "S6_METHOD_THROWS_EXCEPTION": "false",
          "S7_OBJECT_USED_IN_ASSIGNMENT": "false",
          "S8_PRIMITIVE_USED_IN_ASSIGNMENT": "false",
          "S9_METHOD_CALL_WITH_NORMAL_GUARD": "false",
          "ast_info": {
            "dst": "null",
            "dst_parent": "null",
            "dst_parent_type": "null",
            "dst_type": "null",
            "operator": "DEL",
            "src": "case com.google.javascript.rhino.Token.DELPROP :",
            "src_parent": "switch (value.getType()) {\n    case com.google.javascript.rhino.Token.ASSIGN :\n        return com.google.javascript.jscomp.NodeUtil.isImmutableValue(value.getLastChild()) || (locals.apply(value) && com.google.javascript.jscomp.NodeUtil.evaluatesToLocalValue(value.getLastChild(), locals));\n    case com.google.javascript.rhino.Token.COMMA :\n        return com.google.javascript.jscomp.NodeUtil.evaluatesToLocalValue(value.getLastChild(), locals);\n    case com.google.javascript.rhino.Token.AND :\n    case com.google.javascript.rhino.Token.OR :\n        return com.google.javascript.jscomp.NodeUtil.evaluatesToLocalValue(value.getFirstChild(), locals) && com.google.javascript.jscomp.NodeUtil.evaluatesToLocalValue(value.getLastChild(), locals);\n    case com.google.javascript.rhino.Token.HOOK :\n        return com.google.javascript.jscomp.NodeUtil.evaluatesToLocalValue(value.getFirstChild().getNext(), locals) && com.google.javascript.jscomp.NodeUtil.evaluatesToLocalValue(value.getLastChild(), locals);\n    case com.google.javascript.rhino.Token.INC :\n    case com.google.javascript.rhino.Token.DEC :\n        if (value.getBooleanProp(Node.INCRDECR_PROP)) {\n            return com.google.javascript.jscomp.NodeUtil.evaluatesToLocalValue(value.getFirstChild(), locals);\n        } else {\n            return true;\n        }\n    case com.google.javascript.rhino.Token.THIS :\n        return locals.apply(value);\n    case com.google.javascript.rhino.Token.NAME :\n        return com.google.javascript.jscomp.NodeUtil.isImmutableValue(value) || locals.apply(value);\n    case com.google.javascript.rhino.Token.GETELEM :\n    case com.google.javascript.rhino.Token.GETPROP :\n        return locals.apply(value);\n    case com.google.javascript.rhino.Token.CALL :\n        return (com.google.javascript.jscomp.NodeUtil.callHasLocalResult(value) || com.google.javascript.jscomp.NodeUtil.isToStringMethodCall(value)) || locals.apply(value);\n    case com.google.javascript.rhino.Token.NEW :\n        return com.google.javascript.jscomp.NodeUtil.newHasLocalResult(value) || locals.apply(value);\n    case com.google.javascript.rhino.Token.FUNCTION :\n    case com.google.javascript.rhino.Token.REGEXP :\n    case com.google.javascript.rhino.Token.ARRAYLIT :\n    case com.google.javascript.rhino.Token.OBJECTLIT :\n        return true;\n    case com.google.javascript.rhino.Token.DELPROP :\n    case com.google.javascript.rhino.Token.IN :\n        return true;\n    default :\n        if ((com.google.javascript.jscomp.NodeUtil.isAssignmentOp(value) || com.google.javascript.jscomp.NodeUtil.isSimpleOperator(value)) || com.google.javascript.jscomp.NodeUtil.isImmutableValue(value)) {\n            return true;\n        }\n        throw new java.lang.IllegalStateException(((\"Unexpected expression node\" + value) + \"\\n parent:\") + value.getParent());\n}",
            "src_parent_type": "Switch",
            "src_type": "Case"
          }
        },
        {
          "FEATURES_METHOD_INVOCATION": {},
          "FEATURES_TYPEACCESS": {},
          "FEATURES_VARS": {},
          "S10_METHOD_CALL_WITH_NULL_GUARD": "false",
          "S11_FAULTY_CLASS_EXCEPTION_TYPE": "false",
          "S12_METHOD_CALL_WITH_TRY_CATCH": "false",
          "S13_TYPE_OF_FAULTY_STATEMENT_AFTER_1": "",
          "S13_TYPE_OF_FAULTY_STATEMENT_AFTER_2": "",
          "S13_TYPE_OF_FAULTY_STATEMENT_AFTER_3": "",
          "S13_TYPE_OF_FAULTY_STATEMENT_BEFORE_1": "",
          "S13_TYPE_OF_FAULTY_STATEMENT_BEFORE_2": "",
          "S13_TYPE_OF_FAULTY_STATEMENT_BEFORE_3": "",
          "S14_TYPE_OF_FAULTY_STATEMENT_PARENT": "Method",
          "S15_HAS_OBJECTIVE_METHOD_CALL": "true",
          "S16_HAS_Invocations_Prone_Exception": "false",
          "S18_In_Synchronized_Method": "false",
          "S1_LOCAL_VAR_NOT_ASSIGNED": "false",
          "S1_LOCAL_VAR_NOT_USED": "false",
          "S2_SIMILAR_OBJECT_TYPE_WITH_NORMAL_GUARD": "false",
          "S2_SIMILAR_OBJECT_TYPE_WITH_NULL_GUARD": "false",
          "S3_TYPE_OF_FAULTY_STATEMENT": "Switch",
          "S4_Field_NOT_ASSIGNED": "false",
          "S4_Field_NOT_USED": "false",
          "S5_SIMILAR_PRIMITIVE_TYPE_WITH_NORMAL_GUARD": "false",
          "S5_SIMILAR_PRIMITIVE_TYPE_WITH_NULL_GUARD": "false",
          "S6_METHOD_THROWS_EXCEPTION": "false",
          "S7_OBJECT_USED_IN_ASSIGNMENT": "false",
          "S8_PRIMITIVE_USED_IN_ASSIGNMENT": "false",
          "S9_METHOD_CALL_WITH_NORMAL_GUARD": "false",
          "ast_info": {
            "dst": "return true",
            "dst_parent": "case com.google.javascript.rhino.Token.NOT :\n    return true;",
            "dst_parent_type": "Case",
            "dst_type": "Return",
            "operator": "MOV",
            "src": "return true",
            "src_parent": "case com.google.javascript.rhino.Token.DELPROP :\n    return true;",
            "src_parent_type": "Case",
            "src_type": "Return"
          }
        }
      ],
      "file_name": "NodeUtil"
    }
  ],
  "id": "Closure_80"
}