{
  "files": [
    {
      "features": [
        {
          "FEATURES_METHOD_INVOCATION": {},
          "FEATURES_TYPEACCESS": {},
          "FEATURES_VARS": {},
          "S10_METHOD_CALL_WITH_NULL_GUARD": "false",
          "S12_METHOD_CALL_WITH_TRY_CATCH": "false",
          "S13_TYPE_OF_FAULTY_STATEMENT_AFTER_1": "",
          "S13_TYPE_OF_FAULTY_STATEMENT_AFTER_2": "",
          "S13_TYPE_OF_FAULTY_STATEMENT_AFTER_3": "",
          "S13_TYPE_OF_FAULTY_STATEMENT_BEFORE_1": "",
          "S13_TYPE_OF_FAULTY_STATEMENT_BEFORE_2": "",
          "S13_TYPE_OF_FAULTY_STATEMENT_BEFORE_3": "",
          "S14_TYPE_OF_FAULTY_STATEMENT_PARENT": "Package",
          "S15_HAS_OBJECTIVE_METHOD_CALL": "true",
          "S16_HAS_Invocations_Prone_Exception": "false",
          "S18_In_Synchronized_Method": "false",
          "S1_LOCAL_VAR_NOT_ASSIGNED": "false",
          "S1_LOCAL_VAR_NOT_USED": "false",
          "S2_SIMILAR_OBJECT_TYPE_WITH_NORMAL_GUARD": "false",
          "S2_SIMILAR_OBJECT_TYPE_WITH_NULL_GUARD": "false",
          "S3_TYPE_OF_FAULTY_STATEMENT": "Class",
          "S4_Field_NOT_ASSIGNED": "false",
          "S4_Field_NOT_USED": "false",
          "S5_SIMILAR_PRIMITIVE_TYPE_WITH_NORMAL_GUARD": "false",
          "S5_SIMILAR_PRIMITIVE_TYPE_WITH_NULL_GUARD": "false",
          "S7_OBJECT_USED_IN_ASSIGNMENT": "false",
          "S8_PRIMITIVE_USED_IN_ASSIGNMENT": "false",
          "S9_METHOD_CALL_WITH_NORMAL_GUARD": "false",
          "ast_info": {
            "dst": "null",
            "dst_parent": "null",
            "dst_parent_type": "null",
            "dst_type": "null",
            "operator": "INS",
            "src": "private boolean isSnapshot(org.apache.maven.artifact.versioning.ArtifactVersion version) {\n    return Artifact.SNAPSHOT_VERSION.equals(version.getQualifier());\n}",
            "src_parent": "public class Restriction {\n    private final org.apache.maven.artifact.versioning.ArtifactVersion lowerBound;\n\n    private final boolean lowerBoundInclusive;\n\n    private final org.apache.maven.artifact.versioning.ArtifactVersion upperBound;\n\n    private final boolean upperBoundInclusive;\n\n    public static final org.apache.maven.artifact.versioning.Restriction EVERYTHING = new org.apache.maven.artifact.versioning.Restriction(null, false, null, false);\n\n    public Restriction(org.apache.maven.artifact.versioning.ArtifactVersion lowerBound, boolean lowerBoundInclusive, org.apache.maven.artifact.versioning.ArtifactVersion upperBound, boolean upperBoundInclusive) {\n        this.lowerBound = lowerBound;\n        this.lowerBoundInclusive = lowerBoundInclusive;\n        this.upperBound = upperBound;\n        this.upperBoundInclusive = upperBoundInclusive;\n    }\n\n    public org.apache.maven.artifact.versioning.ArtifactVersion getLowerBound() {\n        return lowerBound;\n    }\n\n    public boolean isLowerBoundInclusive() {\n        return lowerBoundInclusive;\n    }\n\n    public org.apache.maven.artifact.versioning.ArtifactVersion getUpperBound() {\n        return upperBound;\n    }\n\n    public boolean isUpperBoundInclusive() {\n        return upperBoundInclusive;\n    }\n\n    public boolean containsVersion(org.apache.maven.artifact.versioning.ArtifactVersion version) {\n        boolean snapshot = isSnapshot(version);\n        if (lowerBound != null) {\n            int comparison = lowerBound.compareTo(version);\n            if (snapshot && (comparison == 0)) {\n                return true;\n            }\n            if ((comparison == 0) && (!lowerBoundInclusive)) {\n                return false;\n            }\n            if (comparison > 0) {\n                return false;\n            }\n        }\n        if (upperBound != null) {\n            int comparison = upperBound.compareTo(version);\n            if (snapshot && (comparison == 0)) {\n                return true;\n            }\n            if ((comparison == 0) && (!upperBoundInclusive)) {\n                return false;\n            }\n            if (comparison < 0) {\n                return false;\n            }\n        }\n        if ((lowerBound != null) || (upperBound != null)) {\n            return !snapshot;\n        }\n        return true;\n    }\n\n    private boolean isSnapshot(org.apache.maven.artifact.versioning.ArtifactVersion version) {\n        return Artifact.SNAPSHOT_VERSION.equals(version.getQualifier());\n    }\n\n    @java.lang.Override\n    public int hashCode() {\n        int result = 13;\n        if (lowerBound == null) {\n            result += 1;\n        } else {\n            result += lowerBound.hashCode();\n        }\n        result *= (lowerBoundInclusive) ? 1 : 2;\n        if (upperBound == null) {\n            result -= 3;\n        } else {\n            result -= upperBound.hashCode();\n        }\n        result *= (upperBoundInclusive) ? 2 : 3;\n        return result;\n    }\n\n    @java.lang.Override\n    public boolean equals(java.lang.Object other) {\n        if (this == other) {\n            return true;\n        }\n        if (!(other instanceof org.apache.maven.artifact.versioning.Restriction)) {\n            return false;\n        }\n        org.apache.maven.artifact.versioning.Restriction restriction = ((org.apache.maven.artifact.versioning.Restriction) (other));\n        if (lowerBound != null) {\n            if (!lowerBound.equals(restriction.lowerBound)) {\n                return false;\n            }\n        } else if (restriction.lowerBound != null) {\n            return false;\n        }\n        if (lowerBoundInclusive != restriction.lowerBoundInclusive) {\n            return false;\n        }\n        if (upperBound != null) {\n            if (!upperBound.equals(restriction.upperBound)) {\n                return false;\n            }\n        } else if (restriction.upperBound != null) {\n            return false;\n        }\n        if (upperBoundInclusive != restriction.upperBoundInclusive) {\n            return false;\n        }\n        return true;\n    }\n\n    public java.lang.String toString() {\n        java.lang.StringBuilder buf = new java.lang.StringBuilder();\n        buf.append(isLowerBoundInclusive() ? \"[\" : \"(\");\n        if (getLowerBound() != null) {\n            buf.append(getLowerBound().toString());\n        }\n        buf.append(\",\");\n        if (getUpperBound() != null) {\n            buf.append(getUpperBound().toString());\n        }\n        buf.append(isUpperBoundInclusive() ? \"]\" : \")\");\n        return buf.toString();\n    }\n}",
            "src_parent_type": "Class",
            "src_type": "Method"
          }
        },
        {
          "FEATURES_METHOD_INVOCATION": {},
          "FEATURES_TYPEACCESS": {},
          "FEATURES_VARS": {},
          "S10_METHOD_CALL_WITH_NULL_GUARD": "false",
          "S11_FAULTY_CLASS_EXCEPTION_TYPE": "false",
          "S12_METHOD_CALL_WITH_TRY_CATCH": "false",
          "S13_TYPE_OF_FAULTY_STATEMENT_AFTER_1": "",
          "S13_TYPE_OF_FAULTY_STATEMENT_AFTER_2": "",
          "S13_TYPE_OF_FAULTY_STATEMENT_AFTER_3": "",
          "S13_TYPE_OF_FAULTY_STATEMENT_BEFORE_1": "",
          "S13_TYPE_OF_FAULTY_STATEMENT_BEFORE_2": "",
          "S13_TYPE_OF_FAULTY_STATEMENT_BEFORE_3": "",
          "S14_TYPE_OF_FAULTY_STATEMENT_PARENT": "Class",
          "S15_HAS_OBJECTIVE_METHOD_CALL": "false",
          "S16_HAS_Invocations_Prone_Exception": "false",
          "S18_In_Synchronized_Method": "false",
          "S1_LOCAL_VAR_NOT_ASSIGNED": "false",
          "S1_LOCAL_VAR_NOT_USED": "false",
          "S2_SIMILAR_OBJECT_TYPE_WITH_NORMAL_GUARD": "false",
          "S2_SIMILAR_OBJECT_TYPE_WITH_NULL_GUARD": "false",
          "S3_TYPE_OF_FAULTY_STATEMENT": "Method",
          "S4_Field_NOT_ASSIGNED": "false",
          "S4_Field_NOT_USED": "false",
          "S5_SIMILAR_PRIMITIVE_TYPE_WITH_NORMAL_GUARD": "false",
          "S5_SIMILAR_PRIMITIVE_TYPE_WITH_NULL_GUARD": "false",
          "S7_OBJECT_USED_IN_ASSIGNMENT": "false",
          "S8_PRIMITIVE_USED_IN_ASSIGNMENT": "false",
          "S9_METHOD_CALL_WITH_NORMAL_GUARD": "false",
          "ast_info": {
            "dst": "null",
            "dst_parent": "null",
            "dst_parent_type": "null",
            "dst_type": "null",
            "operator": "INS",
            "src": "boolean snapshot = isSnapshot(version)",
            "src_parent": "{\n    boolean snapshot = isSnapshot(version);\n    if (lowerBound != null) {\n        int comparison = lowerBound.compareTo(version);\n        if (snapshot && (comparison == 0)) {\n            return true;\n        }\n        if ((comparison == 0) && (!lowerBoundInclusive)) {\n            return false;\n        }\n        if (comparison > 0) {\n            return false;\n        }\n    }\n    if (upperBound != null) {\n        int comparison = upperBound.compareTo(version);\n        if (snapshot && (comparison == 0)) {\n            return true;\n        }\n        if ((comparison == 0) && (!upperBoundInclusive)) {\n            return false;\n        }\n        if (comparison < 0) {\n            return false;\n        }\n    }\n    if ((lowerBound != null) || (upperBound != null)) {\n        return !snapshot;\n    }\n    return true;\n}",
            "src_parent_type": "Block",
            "src_type": "LocalVariable"
          }
        },
        {
          "FEATURES_METHOD_INVOCATION": {},
          "FEATURES_TYPEACCESS": {},
          "FEATURES_VARS": {},
          "S10_METHOD_CALL_WITH_NULL_GUARD": "false",
          "S11_FAULTY_CLASS_EXCEPTION_TYPE": "false",
          "S12_METHOD_CALL_WITH_TRY_CATCH": "false",
          "S13_TYPE_OF_FAULTY_STATEMENT_AFTER_1": "",
          "S13_TYPE_OF_FAULTY_STATEMENT_AFTER_2": "",
          "S13_TYPE_OF_FAULTY_STATEMENT_AFTER_3": "",
          "S13_TYPE_OF_FAULTY_STATEMENT_BEFORE_1": "",
          "S13_TYPE_OF_FAULTY_STATEMENT_BEFORE_2": "",
          "S13_TYPE_OF_FAULTY_STATEMENT_BEFORE_3": "",
          "S14_TYPE_OF_FAULTY_STATEMENT_PARENT": "Class",
          "S15_HAS_OBJECTIVE_METHOD_CALL": "false",
          "S16_HAS_Invocations_Prone_Exception": "false",
          "S18_In_Synchronized_Method": "false",
          "S1_LOCAL_VAR_NOT_ASSIGNED": "false",
          "S1_LOCAL_VAR_NOT_USED": "false",
          "S2_SIMILAR_OBJECT_TYPE_WITH_NORMAL_GUARD": "false",
          "S2_SIMILAR_OBJECT_TYPE_WITH_NULL_GUARD": "false",
          "S3_TYPE_OF_FAULTY_STATEMENT": "Method",
          "S4_Field_NOT_ASSIGNED": "false",
          "S4_Field_NOT_USED": "false",
          "S5_SIMILAR_PRIMITIVE_TYPE_WITH_NORMAL_GUARD": "false",
          "S5_SIMILAR_PRIMITIVE_TYPE_WITH_NULL_GUARD": "false",
          "S7_OBJECT_USED_IN_ASSIGNMENT": "false",
          "S8_PRIMITIVE_USED_IN_ASSIGNMENT": "false",
          "S9_METHOD_CALL_WITH_NORMAL_GUARD": "false",
          "ast_info": {
            "dst": "null",
            "dst_parent": "null",
            "dst_parent_type": "null",
            "dst_type": "null",
            "operator": "INS",
            "src": "if ((lowerBound != null) || (upperBound != null)) {\n    return !snapshot;\n}",
            "src_parent": "{\n    boolean snapshot = isSnapshot(version);\n    if (lowerBound != null) {\n        int comparison = lowerBound.compareTo(version);\n        if (snapshot && (comparison == 0)) {\n            return true;\n        }\n        if ((comparison == 0) && (!lowerBoundInclusive)) {\n            return false;\n        }\n        if (comparison > 0) {\n            return false;\n        }\n    }\n    if (upperBound != null) {\n        int comparison = upperBound.compareTo(version);\n        if (snapshot && (comparison == 0)) {\n            return true;\n        }\n        if ((comparison == 0) && (!upperBoundInclusive)) {\n            return false;\n        }\n        if (comparison < 0) {\n            return false;\n        }\n    }\n    if ((lowerBound != null) || (upperBound != null)) {\n        return !snapshot;\n    }\n    return true;\n}",
            "src_parent_type": "Block",
            "src_type": "If"
          }
        },
        {
          "FEATURES_METHOD_INVOCATION": {},
          "FEATURES_TYPEACCESS": {},
          "FEATURES_VARS": {},
          "S10_METHOD_CALL_WITH_NULL_GUARD": "false",
          "S11_FAULTY_CLASS_EXCEPTION_TYPE": "false",
          "S12_METHOD_CALL_WITH_TRY_CATCH": "false",
          "S13_TYPE_OF_FAULTY_STATEMENT_AFTER_1": "If",
          "S13_TYPE_OF_FAULTY_STATEMENT_AFTER_2": "Return",
          "S13_TYPE_OF_FAULTY_STATEMENT_AFTER_3": "",
          "S13_TYPE_OF_FAULTY_STATEMENT_BEFORE_1": "",
          "S13_TYPE_OF_FAULTY_STATEMENT_BEFORE_2": "",
          "S13_TYPE_OF_FAULTY_STATEMENT_BEFORE_3": "",
          "S14_TYPE_OF_FAULTY_STATEMENT_PARENT": "Method",
          "S15_HAS_OBJECTIVE_METHOD_CALL": "false",
          "S16_HAS_Invocations_Prone_Exception": "false",
          "S18_In_Synchronized_Method": "false",
          "S1_LOCAL_VAR_NOT_ASSIGNED": "false",
          "S1_LOCAL_VAR_NOT_USED": "false",
          "S2_SIMILAR_OBJECT_TYPE_WITH_NORMAL_GUARD": "false",
          "S2_SIMILAR_OBJECT_TYPE_WITH_NULL_GUARD": "false",
          "S3_TYPE_OF_FAULTY_STATEMENT": "If",
          "S4_Field_NOT_ASSIGNED": "false",
          "S4_Field_NOT_USED": "false",
          "S5_SIMILAR_PRIMITIVE_TYPE_WITH_NORMAL_GUARD": "false",
          "S5_SIMILAR_PRIMITIVE_TYPE_WITH_NULL_GUARD": "false",
          "S6_METHOD_THROWS_EXCEPTION": "false",
          "S7_OBJECT_USED_IN_ASSIGNMENT": "false",
          "S8_PRIMITIVE_USED_IN_ASSIGNMENT": "false",
          "S9_METHOD_CALL_WITH_NORMAL_GUARD": "false",
          "ast_info": {
            "dst": "null",
            "dst_parent": "null",
            "dst_parent_type": "null",
            "dst_type": "null",
            "operator": "INS",
            "src": "if (snapshot && (comparison == 0)) {\n    return true;\n}",
            "src_parent": "{\n    int comparison = lowerBound.compareTo(version);\n    if (snapshot && (comparison == 0)) {\n        return true;\n    }\n    if ((comparison == 0) && (!lowerBoundInclusive)) {\n        return false;\n    }\n    if (comparison > 0) {\n        return false;\n    }\n}",
            "src_parent_type": "Block",
            "src_type": "If"
          }
        },
        {
          "FEATURES_METHOD_INVOCATION": {},
          "FEATURES_TYPEACCESS": {},
          "FEATURES_VARS": {},
          "S10_METHOD_CALL_WITH_NULL_GUARD": "false",
          "S11_FAULTY_CLASS_EXCEPTION_TYPE": "false",
          "S12_METHOD_CALL_WITH_TRY_CATCH": "false",
          "S13_TYPE_OF_FAULTY_STATEMENT_AFTER_1": "Return",
          "S13_TYPE_OF_FAULTY_STATEMENT_AFTER_2": "",
          "S13_TYPE_OF_FAULTY_STATEMENT_AFTER_3": "",
          "S13_TYPE_OF_FAULTY_STATEMENT_BEFORE_1": "If",
          "S13_TYPE_OF_FAULTY_STATEMENT_BEFORE_2": "",
          "S13_TYPE_OF_FAULTY_STATEMENT_BEFORE_3": "",
          "S14_TYPE_OF_FAULTY_STATEMENT_PARENT": "Method",
          "S15_HAS_OBJECTIVE_METHOD_CALL": "false",
          "S16_HAS_Invocations_Prone_Exception": "false",
          "S18_In_Synchronized_Method": "false",
          "S1_LOCAL_VAR_NOT_ASSIGNED": "false",
          "S1_LOCAL_VAR_NOT_USED": "false",
          "S2_SIMILAR_OBJECT_TYPE_WITH_NORMAL_GUARD": "false",
          "S2_SIMILAR_OBJECT_TYPE_WITH_NULL_GUARD": "false",
          "S3_TYPE_OF_FAULTY_STATEMENT": "If",
          "S4_Field_NOT_ASSIGNED": "false",
          "S4_Field_NOT_USED": "false",
          "S5_SIMILAR_PRIMITIVE_TYPE_WITH_NORMAL_GUARD": "false",
          "S5_SIMILAR_PRIMITIVE_TYPE_WITH_NULL_GUARD": "false",
          "S6_METHOD_THROWS_EXCEPTION": "false",
          "S7_OBJECT_USED_IN_ASSIGNMENT": "false",
          "S8_PRIMITIVE_USED_IN_ASSIGNMENT": "false",
          "S9_METHOD_CALL_WITH_NORMAL_GUARD": "false",
          "ast_info": {
            "dst": "null",
            "dst_parent": "null",
            "dst_parent_type": "null",
            "dst_type": "null",
            "operator": "INS",
            "src": "if (snapshot && (comparison == 0)) {\n    return true;\n}",
            "src_parent": "{\n    int comparison = upperBound.compareTo(version);\n    if (snapshot && (comparison == 0)) {\n        return true;\n    }\n    if ((comparison == 0) && (!upperBoundInclusive)) {\n        return false;\n    }\n    if (comparison < 0) {\n        return false;\n    }\n}",
            "src_parent_type": "Block",
            "src_type": "If"
          }
        }
      ],
      "file_name": "Restriction"
    }
  ],
  "id": "maven_5ffd8903"
}